uspekpy/__init__.py
uspekpy/simulation.py
uspekpy/uspek.py
uspekpy/wrapper.py
uspekpy-1.0.1.dist-info/METADATA
uspekpy-1.0.1.dist-info/WHEEL
uspekpy-1.0.1.dist-info/licenses/LICENSE
uspekpy-1.0.1.dist-info/RECORD
