Metadata-Version: 2.3
Name: uspekpy
Version: 1.0.1
Summary: Radiation protection quantities for x-rays with uncertainties using SpekPy and Monte Carlo techniques
Project-URL: Repository, https://github.com/lmri-met/uspekpy
Project-URL: Documentation, https://github.com/lmri-met/uspekpy#readme
Project-URL: Issues, https://github.com/lmri-met/uspekpy/issues
Author-email: Paz Aviles <Paz.Aviles@ciemat.es>, Xandra Campo <xandra.campo@ciemat.es>
Maintainer-email: Xandra Campo <xandra.campo@ciemat.es>, Paz Aviles <Paz.Aviles@ciemat.es>
License:                     GNU GENERAL PUBLIC LICENSE
License-File: LICENSE
Keywords: monte carlo,spectrum,uncertainty,x-rays
Classifier: Development Status :: 4 - Beta
Classifier: Intended Audience :: Science/Research
Classifier: License :: OSI Approved :: GNU General Public License v3 (GPLv3)
Classifier: Operating System :: OS Independent
Classifier: Programming Language :: Python
Classifier: Programming Language :: Python :: 3
Classifier: Programming Language :: Python :: 3.8
Classifier: Programming Language :: Python :: 3.9
Classifier: Programming Language :: Python :: 3.10
Classifier: Programming Language :: Python :: 3.11
Classifier: Programming Language :: Python :: 3.12
Classifier: Programming Language :: Python :: Implementation :: CPython
Classifier: Topic :: Scientific/Engineering :: Physics
Requires-Python: >=3.8
Requires-Dist: openpyxl>=3.1.2
Requires-Dist: pandas>=2.2.2
Requires-Dist: spekpy>=2.0.11.1
